pyxi_couchbase_client/__init__.py
pyxi_couchbase_client/couchbase_client.py
pyxi_couchbase_client/secret_provider.py
pyxi_couchbase_client-0.0.10.dist-info/LICENSE
pyxi_couchbase_client-0.0.10.dist-info/METADATA
pyxi_couchbase_client-0.0.10.dist-info/WHEEL
pyxi_couchbase_client-0.0.10.dist-info/top_level.txt
pyxi_couchbase_client-0.0.10.dist-info/RECORD
