Metadata-Version: 2.1
Name: pyxi-couchbase-client
Version: 0.0.10
Summary: A basic couchbase client for python.
Home-page: https://github.com/stiproot/py-couchbase-client
Author: Simon Stipcich
Author-email: stipcich.simon@gmail.com
License: MIT
Keywords: python,package,couchbase,beta
Classifier: Intended Audience :: Developers
Classifier: License :: OSI Approved :: MIT License
Classifier: Programming Language :: Python :: 3.11
License-File: LICENSE
Requires-Dist: environs ==9.5.0
Requires-Dist: couchbase ==4.1.8
